cve_py/__init__.py
cve_py/__main__.py
cve_py/api.py
cve_py/args.py
cve_py/database.py
cve_py/mail.py
cve_py/smtp.py
cve_py-1.2.4.dist-info/LICENSE
cve_py-1.2.4.dist-info/METADATA
cve_py-1.2.4.dist-info/WHEEL
cve_py-1.2.4.dist-info/top_level.txt
cve_py-1.2.4.dist-info/RECORD
