Metadata-Version: 2.1
Name: cve-py
Version: 1.2.4
Summary: Tracks CVEs, stores them in a local database, and sends email reports
Author: Pavel Sushko
Author-email: SB Software Inc. <info@sbsoftware.ca>
License: MIT
Classifier: Development Status :: 5 - Production/Stable
Classifier: Environment :: Console
Classifier: Intended Audience :: Developers
Classifier: License :: OSI Approved :: MIT License
Classifier: Operating System :: MacOS :: MacOS X
Classifier: Operating System :: Microsoft :: Windows
Classifier: Operating System :: POSIX :: Linux
Classifier: Programming Language :: Python :: 3
Classifier: Programming Language :: Python :: 3 :: Only
Classifier: Programming Language :: Python :: 3.6
Classifier: Programming Language :: Python :: 3.7
Classifier: Programming Language :: Python :: 3.8
Classifier: Programming Language :: Python :: 3.9
Classifier: Programming Language :: Python :: 3.10
Classifier: Programming Language :: Python :: 3.11
Requires-Python: <3.12,>=3.6
License-File: LICENSE
Requires-Dist: defusedxml (>=0.7.1)
Requires-Dist: requests (>=2.28.2)
Requires-Dist: google-api-core (>=2.11.0)
Requires-Dist: google-api-python-client (>=2.82.0)
Requires-Dist: google-auth (>=2.16.3)
Requires-Dist: google-auth-httplib2 (>=0.1.0)
Requires-Dist: google-auth-oauthlib (>=1.0.0)
Requires-Dist: googleapis-common-protos (>=1.59.0)
